{
  "kind": "batch-canary",
  "node": "hetzner",
  "ts": 1781425588,
  "queue": {
    "claimed": 9601,
    "dead": 1,
    "done": 1909094,
    "failed": 1,
    "pending": 1942065
  },
  "enrich_done_per_min": 1024.5,
  "pg": {
    "total_conns": 83,
    "active_conns": 11,
    "max_connections": 200,
    "conn_ceiling": 85,
    "pg_connect_ms": 9.4
  },
  "loadavg": {
    "1m": 4.38818359375,
    "5m": 5.46435546875,
    "15m": 5.60302734375
  },
  "sev1_flags": [],
  "healthy": true,
  "note": "done-rate from timestamped delta over the sample window; conns/load/pg_isready are the SEV-1 monitor. If sev1_flags non-empty, back off the canary."
}