{
  "kind": "batch-canary",
  "node": "hetzner",
  "ts": 1781129285,
  "queue": {
    "claimed": 5993,
    "done": 2496767,
    "pending": 298470
  },
  "enrich_done_per_min": 1484.7,
  "pg": {
    "total_conns": 76,
    "active_conns": 5,
    "max_connections": 100,
    "conn_ceiling": 85,
    "pg_connect_ms": 19.2
  },
  "loadavg": {
    "1m": 7.0556640625,
    "5m": 5.0810546875,
    "15m": 4.50634765625
  },
  "sev1_flags": [],
  "healthy": true,
  "note": "done-rate from timestamped delta over the sample window; conns/load/pg_isready are the SEV-1 monitor. If sev1_flags non-empty, back off the canary."
}