{
  "kind": "batch-canary",
  "node": "hetzner",
  "ts": 1781249403,
  "queue": {
    "claimed": 2083,
    "done": 1734480,
    "pending": 1470371
  },
  "enrich_done_per_min": 1526.6,
  "pg": {
    "total_conns": 70,
    "active_conns": 3,
    "max_connections": 100,
    "conn_ceiling": 85,
    "pg_connect_ms": 14.6
  },
  "loadavg": {
    "1m": 6.37890625,
    "5m": 6.47900390625,
    "15m": 6.75390625
  },
  "sev1_flags": [],
  "healthy": true,
  "note": "done-rate from timestamped delta over the sample window; conns/load/pg_isready are the SEV-1 monitor. If sev1_flags non-empty, back off the canary."
}