{
  "kind": "batch-canary",
  "node": "hetzner",
  "ts": 1781137576,
  "queue": {
    "claimed": 4296,
    "done": 1495262,
    "pending": 1306722
  },
  "enrich_done_per_min": 149.3,
  "pg": {
    "total_conns": 86,
    "active_conns": 68,
    "max_connections": 100,
    "conn_ceiling": 85,
    "pg_connect_ms": 13.3
  },
  "loadavg": {
    "1m": 5.8798828125,
    "5m": 4.98779296875,
    "15m": 5.39794921875
  },
  "sev1_flags": [
    "conns 86 > ceiling 85"
  ],
  "healthy": false,
  "note": "done-rate from timestamped delta over the sample window; conns/load/pg_isready are the SEV-1 monitor. If sev1_flags non-empty, back off the canary."
}