{
  "kind": "batch-canary",
  "node": "hetzner",
  "ts": 1781149005,
  "queue": {
    "claimed": 4255,
    "done": 1479980,
    "pending": 1327139
  },
  "enrich_done_per_min": 1062.9,
  "pg": {
    "total_conns": 84,
    "active_conns": 58,
    "max_connections": 100,
    "conn_ceiling": 85,
    "pg_connect_ms": 38.9
  },
  "loadavg": {
    "1m": 16.798828125,
    "5m": 5.86865234375,
    "15m": 4.94189453125
  },
  "sev1_flags": [
    "load1 16.8 high"
  ],
  "healthy": false,
  "note": "done-rate from timestamped delta over the sample window; conns/load/pg_isready are the SEV-1 monitor. If sev1_flags non-empty, back off the canary."
}