{
  "kind": "batch-canary",
  "node": "hetzner",
  "ts": 1781298254,
  "queue": {
    "claimed": 2362,
    "done": 1775743,
    "pending": 1523593
  },
  "enrich_done_per_min": 494.0,
  "pg": {
    "total_conns": 77,
    "active_conns": 62,
    "max_connections": 100,
    "conn_ceiling": 85,
    "pg_connect_ms": 14.9
  },
  "loadavg": {
    "1m": 8.830078125,
    "5m": 3.9189453125,
    "15m": 3.81640625
  },
  "sev1_flags": [
    "load1 8.8 high"
  ],
  "healthy": false,
  "note": "done-rate from timestamped delta over the sample window; conns/load/pg_isready are the SEV-1 monitor. If sev1_flags non-empty, back off the canary."
}