{
  "kind": "batch-canary",
  "node": "hetzner",
  "ts": 1781379581,
  "queue": {
    "claimed": 2181,
    "done": 1861058,
    "pending": 1711799
  },
  "enrich_done_per_min": 161.0,
  "pg": {
    "total_conns": 85,
    "active_conns": 72,
    "max_connections": 100,
    "conn_ceiling": 85,
    "pg_connect_ms": 13.3
  },
  "loadavg": {
    "1m": 0.98193359375,
    "5m": 4.29541015625,
    "15m": 6.51025390625
  },
  "sev1_flags": [],
  "healthy": true,
  "note": "done-rate from timestamped delta over the sample window; conns/load/pg_isready are the SEV-1 monitor. If sev1_flags non-empty, back off the canary."
}