{
  "kind": "batch-canary",
  "node": "hetzner",
  "ts": 1781350194,
  "queue": {
    "claimed": 2035,
    "done": 1901083,
    "pending": 1596749
  },
  "enrich_done_per_min": 1291.0,
  "pg": {
    "total_conns": 72,
    "active_conns": 1,
    "max_connections": 100,
    "conn_ceiling": 85,
    "pg_connect_ms": 9.2
  },
  "loadavg": {
    "1m": 6.7626953125,
    "5m": 6.64892578125,
    "15m": 7.0888671875
  },
  "sev1_flags": [],
  "healthy": true,
  "note": "done-rate from timestamped delta over the sample window; conns/load/pg_isready are the SEV-1 monitor. If sev1_flags non-empty, back off the canary."
}