{
  "kind": "batch-canary",
  "node": "hetzner",
  "ts": 1781380365,
  "queue": {
    "claimed": 2060,
    "done": 1862196,
    "pending": 1710782
  },
  "enrich_done_per_min": 5.0,
  "pg": {
    "total_conns": 93,
    "active_conns": 83,
    "max_connections": 100,
    "conn_ceiling": 85,
    "pg_connect_ms": 15.0
  },
  "loadavg": {
    "1m": 0.94287109375,
    "5m": 3.26171875,
    "15m": 5.4208984375
  },
  "sev1_flags": [
    "conns 93 > ceiling 85"
  ],
  "healthy": false,
  "note": "done-rate from timestamped delta over the sample window; conns/load/pg_isready are the SEV-1 monitor. If sev1_flags non-empty, back off the canary."
}