{
  "kind": "batch-canary",
  "node": "hetzner",
  "ts": 1781116131,
  "queue": {
    "claimed": 2337,
    "done": 2625390,
    "pending": 168423
  },
  "enrich_done_per_min": 1571.5,
  "pg": {
    "total_conns": 74,
    "active_conns": 1,
    "max_connections": 100,
    "conn_ceiling": 85,
    "pg_connect_ms": 14.4
  },
  "loadavg": {
    "1m": 3.634765625,
    "5m": 3.91357421875,
    "15m": 3.8994140625
  },
  "sev1_flags": [],
  "healthy": true,
  "note": "done-rate from timestamped delta over the sample window; conns/load/pg_isready are the SEV-1 monitor. If sev1_flags non-empty, back off the canary."
}