{
  "kind": "batch-canary",
  "node": "hetzner",
  "ts": 1781253439,
  "queue": {
    "claimed": 2226,
    "done": 1751449,
    "pending": 1457127
  },
  "enrich_done_per_min": 34.8,
  "pg": {
    "total_conns": 83,
    "active_conns": 70,
    "max_connections": 100,
    "conn_ceiling": 85,
    "pg_connect_ms": 14.6
  },
  "loadavg": {
    "1m": 3.11669921875,
    "5m": 7.01220703125,
    "15m": 7.0751953125
  },
  "sev1_flags": [],
  "healthy": true,
  "note": "done-rate from timestamped delta over the sample window; conns/load/pg_isready are the SEV-1 monitor. If sev1_flags non-empty, back off the canary."
}