{
  "kind": "batch-canary",
  "node": "hetzner",
  "ts": 1781277303,
  "queue": {
    "claimed": 2047,
    "done": 1757048,
    "pending": 1526703
  },
  "enrich_done_per_min": 1201.1,
  "pg": {
    "total_conns": 76,
    "active_conns": 6,
    "max_connections": 100,
    "conn_ceiling": 85,
    "pg_connect_ms": 13.9
  },
  "loadavg": {
    "1m": 5.453125,
    "5m": 5.943359375,
    "15m": 5.8017578125
  },
  "sev1_flags": [],
  "healthy": true,
  "note": "done-rate from timestamped delta over the sample window; conns/load/pg_isready are the SEV-1 monitor. If sev1_flags non-empty, back off the canary."
}