{
  "kind": "batch-canary",
  "node": "hetzner",
  "ts": 1781227559,
  "queue": {
    "claimed": 2260,
    "done": 1644184,
    "pending": 1406242
  },
  "enrich_done_per_min": 1436.7,
  "pg": {
    "total_conns": 70,
    "active_conns": 1,
    "max_connections": 100,
    "conn_ceiling": 85,
    "pg_connect_ms": 13.4
  },
  "loadavg": {
    "1m": 4.28076171875,
    "5m": 5.92529296875,
    "15m": 6.04443359375
  },
  "sev1_flags": [],
  "healthy": true,
  "note": "done-rate from timestamped delta over the sample window; conns/load/pg_isready are the SEV-1 monitor. If sev1_flags non-empty, back off the canary."
}