{
  "kind": "batch-canary",
  "node": "hetzner",
  "ts": 1781267158,
  "queue": {
    "claimed": 2732,
    "done": 1734462,
    "pending": 1542509
  },
  "enrich_done_per_min": 0.0,
  "pg": {
    "total_conns": 85,
    "active_conns": 75,
    "max_connections": 100,
    "conn_ceiling": 85,
    "pg_connect_ms": 14.7
  },
  "loadavg": {
    "1m": 2.92724609375,
    "5m": 6.18115234375,
    "15m": 5.91162109375
  },
  "sev1_flags": [],
  "healthy": true,
  "note": "done-rate from timestamped delta over the sample window; conns/load/pg_isready are the SEV-1 monitor. If sev1_flags non-empty, back off the canary."
}