{"lane": "enrich", "node": "hetzner", "worker": "pool-27:2429311", "enriched_per_min": 16.84, "enriched_lifetime": 10048, "coverage": {"business_total": 1614637, "website_pct": 32.8, "phone_pct": 29.6, "email_pct": 6.6, "industry_pct": null, "domain_pct": 31.1, "tech_pct": 25.9, "social_any_pct": 18.4, "queue": {"claimed": 1910, "done": 1750412, "pending": 1467716}, "queue_remaining": 1469626}, "coverage_ceiling_note": "company-level fields reachable ~88-92% free; verified personal direct-dials/personal emails are vendor-gated (~65-72% blended) and are NOT claimed here -- personal emails are pattern HINTS only (field='email_pattern', confidence<=0.4).", "ts": 1781256672}