{"lane": "enrich", "node": "hetzner", "worker": "pool-17:175625", "enriched_per_min": 36.34, "enriched_lifetime": 2208, "coverage": {"business_total": 1272753, "website_pct": 9.5, "phone_pct": 11.7, "email_pct": 2.0, "industry_pct": null, "domain_pct": 9.5, "tech_pct": 8.1, "social_any_pct": 5.9, "queue": {"claimed": 1034, "done": 448207, "pending": 2096265}, "queue_remaining": 2097299}, "coverage_ceiling_note": "company-level fields reachable ~88-92% free; verified personal direct-dials/personal emails are vendor-gated (~65-72% blended) and are NOT claimed here -- personal emails are pattern HINTS only (field='email_pattern', confidence<=0.4).", "ts": 1781010378}