{"lane": "enrich", "node": "hetzner", "worker": "hetzner:ubuntu-16gb-nbg1-1:1:30033", "enriched_per_min": 8.19, "enriched_lifetime": 768, "coverage": {"business_total": 15000, "website_pct": 9.4, "phone_pct": 59.4, "email_pct": 1.9, "industry_pct": null, "domain_pct": 9.4, "tech_pct": 7.9, "social_any_pct": 5.8, "queue": {"pending": 9860, "claimed": 258, "done": 4882}, "queue_remaining": 10118}, "coverage_ceiling_note": "company-level fields reachable ~88-92% free; verified personal direct-dials/personal emails are vendor-gated (~65-72% blended) and are NOT claimed here -- personal emails are pattern HINTS only (field='email_pattern', confidence<=0.4).", "ts": 1780972101}