{"lane": "enrich", "node": "hetzner", "worker": "pool-26:241275", "enriched_per_min": 96.77, "enriched_lifetime": 1632, "coverage": {"business_total": 1272872, "website_pct": 14.2, "phone_pct": 15.4, "email_pct": 3.1, "industry_pct": null, "domain_pct": 14.2, "tech_pct": 12.0, "social_any_pct": 8.6, "queue": {"claimed": 2256, "done": 700258, "pending": 1843230}, "queue_remaining": 1845486}, "coverage_ceiling_note": "company-level fields reachable ~88-92% free; verified personal direct-dials/personal emails are vendor-gated (~65-72% blended) and are NOT claimed here -- personal emails are pattern HINTS only (field='email_pattern', confidence<=0.4).", "ts": 1781020361}