{"lane": "enrich", "node": "hetzner", "worker": "hetzner:ubuntu-16gb-nbg1-1:11:40551", "enriched_per_min": 9.55, "enriched_lifetime": 161, "coverage": {"business_total": 15000, "website_pct": 11.6, "phone_pct": 60.3, "email_pct": 2.2, "industry_pct": null, "domain_pct": 11.6, "tech_pct": 9.9, "social_any_pct": 7.2, "queue": {"pending": 8440, "claimed": 219, "done": 6341}, "queue_remaining": 8659}, "coverage_ceiling_note": "company-level fields reachable ~88-92% free; verified personal direct-dials/personal emails are vendor-gated (~65-72% blended) and are NOT claimed here -- personal emails are pattern HINTS only (field='email_pattern', confidence<=0.4).", "ts": 1780972548}