{"lane": "enrich", "node": "hetzner", "worker": "pool-15:506795", "enriched_per_min": 41.92, "enriched_lifetime": 6368, "coverage": {"business_total": 1272872, "website_pct": 21.8, "phone_pct": 21.5, "email_pct": 4.7, "industry_pct": null, "domain_pct": 21.8, "tech_pct": 18.5, "social_any_pct": 13.3, "queue": {"claimed": 1191, "done": 1342654, "pending": 1201899}, "queue_remaining": 1203090}, "coverage_ceiling_note": "company-level fields reachable ~88-92% free; verified personal direct-dials/personal emails are vendor-gated (~65-72% blended) and are NOT claimed here -- personal emails are pattern HINTS only (field='email_pattern', confidence<=0.4).", "ts": 1781050695}