{"lane": "enrich", "node": "hetzner", "worker": "pool-29:1253854", "enriched_per_min": 18.28, "enriched_lifetime": 2720, "coverage": {"business_total": 1471153, "website_pct": 30.6, "phone_pct": 29.1, "email_pct": 6.6, "industry_pct": null, "domain_pct": 30.6, "tech_pct": 25.9, "social_any_pct": 18.6, "queue": {"claimed": 2070, "done": 1538521, "pending": 1401853}, "queue_remaining": 1403923}, "coverage_ceiling_note": "company-level fields reachable ~88-92% free; verified personal direct-dials/personal emails are vendor-gated (~65-72% blended) and are NOT claimed here -- personal emails are pattern HINTS only (field='email_pattern', confidence<=0.4).", "ts": 1781168014}