{"lane": "enrich", "node": "hetzner", "worker": "pool-20:2429309", "enriched_per_min": 13.0, "enriched_lifetime": 17440, "coverage": {"business_total": 1651032, "website_pct": 33.8, "phone_pct": 30.0, "email_pct": 6.6, "industry_pct": null, "domain_pct": 31.9, "tech_pct": 26.2, "social_any_pct": 18.4, "queue": {"claimed": 1992, "done": 1767798, "pending": 1532274}, "queue_remaining": 1534266}, "coverage_ceiling_note": "company-level fields reachable ~88-92% free; verified personal direct-dials/personal emails are vendor-gated (~65-72% blended) and are NOT claimed here -- personal emails are pattern HINTS only (field='email_pattern', confidence<=0.4).", "ts": 1781301318}