{"node": "hetzner", "seq": 9, "status": "heartbeat", "detail": "alive last_seq=9", "counts": {"lane": "enrich", "node": "hetzner", "worker": "hetzner:ubuntu-16gb-nbg1-1:1:30033", "enriched_per_min": 7.26, "enriched_lifetime": 187, "coverage": {"business_total": 10000, "website_pct": 1.2, "phone_pct": 28.8, "email_pct": 0.2, "industry_pct": null, "domain_pct": 1.2, "tech_pct": 1.0, "social_any_pct": 0.8, "queue": {"pending": 9580, "claimed": 25, "done": 395}, "queue_remaining": 9605}, "coverage_ceiling_note": "company-level fields reachable ~88-92% free; verified personal direct-dials/personal emails are vendor-gated (~65-72% blended) and are NOT claimed here -- personal emails are pattern HINTS only (field='email_pattern', confidence<=0.4).", "ts": 1780967214}, "agent": "v3", "ts": 1780967273}