{"lane": "qa_auditor", "node": "hetzner", "audited": 32800, "pass": 1533, "quarantine": 31260, "reenrich": 7, "pass_rate": 0.0467, "avg_completeness": 0.2036, "top_failure_reasons": [["no_website", 22513], ["email_no_email", 5447], ["has_chat:has_chat_code", 2026], ["ok", 1533], ["website_dead", 917], ["website_parked", 357], ["incomplete_0.48_below_0.55", 3], ["incomplete_0.52_below_0.55", 3]], "named_chat_providers": 53, "live_http": true, "live_mx": true, "live_render": false, "verify_on_box": true, "ts": 1781115311}