{"lane": "qa_auditor", "node": "hetzner", "audited": 2600, "pass": 116, "quarantine": 2481, "reenrich": 3, "pass_rate": 0.0446, "avg_completeness": 0.1895, "top_failure_reasons": [["no_website", 1728], ["email_no_email", 474], ["has_chat:has_chat_code", 152], ["ok", 116], ["website_dead", 98], ["website_parked", 29], ["incomplete_0.48_below_0.55", 2], ["incomplete_0.40_below_0.55", 1]], "named_chat_providers": 53, "live_http": true, "live_mx": true, "live_render": false, "verify_on_box": true, "ts": 1781424037}