{"lane": "qa_auditor", "node": "hetzner", "audited": 4400, "pass": 231, "quarantine": 4159, "reenrich": 10, "pass_rate": 0.0525, "avg_completeness": 0.1996, "top_failure_reasons": [["no_website", 2835], ["email_no_email", 787], ["has_chat:has_chat_code", 310], ["ok", 231], ["website_dead", 175], ["website_parked", 52], ["incomplete_0.52_below_0.55", 3], ["incomplete_0.48_below_0.55", 3]], "named_chat_providers": 53, "live_http": true, "live_mx": true, "live_render": false, "verify_on_box": true, "ts": 1781424394}