{"lane": "qa_auditor", "node": "hetzner", "audited": 16800, "pass": 641, "quarantine": 16132, "reenrich": 27, "pass_rate": 0.0382, "avg_completeness": 0.1669, "top_failure_reasons": [["no_website", 12437], ["email_no_email", 2152], ["has_chat:has_chat_code", 878], ["ok", 641], ["website_dead", 486], ["website_parked", 179], ["incomplete_0.52_below_0.55", 11], ["incomplete_0.48_below_0.55", 8]], "named_chat_providers": 53, "live_http": true, "live_mx": true, "live_render": false, "verify_on_box": true, "ts": 1781171948}