{"node": "hetzner", "seq": 129, "lane": "flat", "status": "failed", "detail": "step 2: cmd failed: /opt/atlas/venv/bin/python /opt/atlas/czds_patch.py (rolled back)", "counts": {"lane": "footprint_compact", "apply": false, "dry_run": true, "before": {"db_bytes": 6234535615, "atlas.business": 633061376, "atlas.source_record": 2761826304, "atlas.field_provenance": 759070720, "atlas.enrich_queue": 1513496576}, "queue_done_candidates": 1735840, "queue_pruned": 0, "payload_candidates": 904713, "payload_nulled": 0, "mode": "null_after_extract", "vacuum": "skipped", "after": {"db_bytes": 6234699455, "atlas.business": 633077760, "atlas.source_record": 2761875456, "atlas.field_provenance": 759095296, "atlas.enrich_queue": 1513553920}, "ts": 1781257463}, "agent": "v4", "ts": 1781257504}