{
  "kind": "source-promote",
  "node": "hetzner",
  "ts": 1781174583,
  "summary": {
    "datasets_tried": 41,
    "live_with_rows": 9,
    "new_rows_this_run": 8355,
    "business_total": 1496361
  },
  "sources": [
    {
      "dataset": "nyc_dob_license_info",
      "domain": "data.cityofnewyork.us",
      "fxf": "t8hj-ruu2",
      "status": "no_name_col",
      "cols": [
        ":id",
        ":created_at",
        ":updated_at",
        ":version",
        "license_sl_no",
        "license_type",
        "license_number",
        "last_name"
      ]
    },
    {
      "dataset": "nyc_other_tobacco_products_license",
      "domain": "data.cityofnewyork.us",
      "fxf": "f264-qcv3",
      "source_code": "socrata_f264-qcv3",
      "status": "empty_window",
      "inserted": 0,
      "fetched": 0,
      "mapped_cols": [
        "name",
        "phone",
        "addr_line1",
        "region",
        "postal",
        "lat",
        "lon"
      ]
    },
    {
      "dataset": "chicago_sidewalk_cafe_permits",
      "domain": "data.cityofchicago.org",
      "fxf": "nxj5-ix6z",
      "source_code": "socrata_nxj5-ix6z",
      "status": "live",
      "inserted": 4,
      "fetched": 7,
      "mapped_cols": [
        "name",
        "addr_line1",
        "city",
        "region",
        "postal",
        "lat",
        "lon"
      ]
    },
    {
      "dataset": "chicago_business_owners",
      "domain": "data.cityofchicago.org",
      "fxf": "ezma-pppn",
      "source_code": "socrata_ezma-pppn",
      "status": "caught_up",
      "inserted": 0,
      "fetched": 96,
      "mapped_cols": [
        "name"
      ]
    },
    {
      "dataset": "delaware_business_licenses",
      "domain": "data.delaware.gov",
      "fxf": "5zy2-grhr",
      "source_code": "socrata_5zy2-grhr",
      "status": "caught_up",
      "inserted": 0,
      "fetched": 2000,
      "mapped_cols": [
        "name",
        "city",
        "region",
        "postal",
        "category"
      ]
    },
    {
      "dataset": "delaware_water_well_contractors",
      "domain": "data.delaware.gov",
      "fxf": "2dnk-irgr",
      "status": "no_name_col",
      "cols": [
        ":id",
        ":created_at",
        ":updated_at",
        ":version",
        "licensenumber",
        "licensesubtype",
        "licstatus",
        "licenseexpires"
      ]
    },
    {
      "dataset": "colorado_business_entities",
      "domain": "data.colorado.gov",
      "fxf": "4ykn-tg5h",
      "source_code": "socrata_4ykn-tg5h",
      "status": "caught_up",
      "inserted": 0,
      "fetched": 2000,
      "mapped_cols": [
        "name"
      ]
    },
    {
      "dataset": "denver_active_business_licenses",
      "domain": "data.colorado.gov",
      "fxf": "s9wt-dsfz",
      "source_code": "socrata_s9wt-dsfz",
      "status": "empty_window",
      "inserted": 0,
      "fetched": 0,
      "mapped_cols": [
        "name",
        "category"
      ]
    },
    {
      "dataset": "colorado_liquor_licenses",
      "domain": "data.colorado.gov",
      "fxf": "ier5-5ms2",
      "source_code": "socrata_ier5-5ms2",
      "status": "live",
      "inserted": 1994,
      "fetched": 2000,
      "mapped_cols": [
        "name",
        "addr_line1",
        "city",
        "region",
        "postal",
        "category"
      ]
    },
    {
      "dataset": "colorado_recently_approved_liquor",
      "domain": "data.colorado.gov",
      "fxf": "htyp-tqzh",
      "source_code": "socrata_htyp-tqzh",
      "status": "live",
      "inserted": 272,
      "fetched": 503,
      "mapped_cols": [
        "name",
        "addr_line1",
        "city",
        "region",
        "postal",
        "category"
      ]
    },
    {
      "dataset": "colorado_tobacco_licenses",
      "domain": "data.colorado.gov",
      "fxf": "ejz2-rwds",
      "source_code": "socrata_ejz2-rwds",
      "status": "empty_window",
      "inserted": 0,
      "fetched": 0,
      "mapped_cols": [
        "name",
        "addr_line1",
        "city",
        "region",
        "postal",
        "category"
      ]
    },
    {
      "dataset": "ct_cannabis_retail_locations",
      "domain": "data.ct.gov",
      "fxf": "42yd-3x3d",
      "source_code": "socrata_42yd-3x3d",
      "status": "caught_up",
      "inserted": 0,
      "fetched": 74,
      "mapped_cols": [
        "name",
        "addr_line1",
        "city",
        "postal",
        "category"
      ]
    },
    {
      "dataset": "delaware_historical_business_licenses",
      "domain": "data.delaware.gov",
      "fxf": "khpy-2pnr",
      "source_code": "socrata_khpy-2pnr",
      "status": "empty_window",
      "inserted": 0,
      "fetched": 0,
      "mapped_cols": [
        "name",
        "city",
        "region",
        "postal",
        "category"
      ]
    },
    {
      "dataset": "missouri_new_liquor_licenses",
      "domain": "data.mo.gov",
      "fxf": "dymb-xy5c",
      "source_code": "socrata_dymb-xy5c",
      "status": "live",
      "inserted": 2000,
      "fetched": 2000,
      "mapped_cols": [
        "name",
        "addr_line1",
        "city",
        "region",
        "postal",
        "category"
      ]
    },
    {
      "dataset": "nj_business_search_njsavi",
      "domain": "data.nj.gov",
      "fxf": "tfhb-8beb",
      "status": "http_403"
    },
    {
      "dataset": "new_orleans_occupational_business_licenses",
      "domain": "data.nola.gov",
      "fxf": "hjcd-grvu",
      "status": "no_name_col",
      "cols": [
        ":id",
        ":created_at",
        ":updated_at",
        ":version",
        ":@computed_region_ewbu_t8bu",
        ":@computed_region_k37d_then",
        ":@computed_region_m56f_hbma",
        ":@computed_region_7fw3_kdpf"
      ]
    },
    {
      "dataset": "ny_current_cannabinoid_hemp_licenses",
      "domain": "data.ny.gov",
      "fxf": "4r7n-55mm",
      "source_code": "socrata_4r7n-55mm",
      "status": "caught_up",
      "inserted": 0,
      "fetched": 2000,
      "mapped_cols": [
        "name"
      ]
    },
    {
      "dataset": "ny_registered_tobacco_vapor_dealers",
      "domain": "data.ny.gov",
      "fxf": "55xf-9jat",
      "status": "no_name_col",
      "cols": [
        ":id",
        ":created_at",
        ":updated_at",
        ":version",
        ":@computed_region_wbg7_3whc",
        ":@computed_region_kjdx_g34t",
        ":@computed_region_yamh_8v7k",
        "cor_id"
      ]
    },
    {
      "dataset": "ny_registered_adult_use_cannabis_dealers",
      "domain": "data.ny.gov",
      "fxf": "gttd-5u6y",
      "source_code": "socrata_gttd-5u6y",
      "status": "caught_up",
      "inserted": 0,
      "fetched": 590,
      "mapped_cols": [
        "name"
      ]
    },
    {
      "dataset": "ny_current_ocm_cannabis_licenses",
      "domain": "data.ny.gov",
      "fxf": "jskf-tt3q",
      "source_code": "socrata_jskf-tt3q",
      "status": "caught_up",
      "inserted": 0,
      "fetched": 2000,
      "mapped_cols": [
        "name",
        "region",
        "category"
      ]
    },
    {
      "dataset": "ny_appearance_barber_business_licensees",
      "domain": "data.ny.gov",
      "fxf": "y3u4-jbgh",
      "source_code": "socrata_y3u4-jbgh",
      "status": "caught_up",
      "inserted": 0,
      "fetched": 2000,
      "mapped_cols": [
        "name",
        "city",
        "region",
        "postal",
        "category"
      ]
    },
    {
      "dataset": "ny_mold_contractor_licenses",
      "domain": "data.ny.gov",
      "fxf": "ikqx-ispy",
      "source_code": "socrata_ikqx-ispy",
      "status": "caught_up",
      "inserted": 0,
      "fetched": 2000,
      "mapped_cols": [
        "name",
        "phone",
        "addr_line1",
        "city",
        "region",
        "postal",
        "category"
      ]
    },
    {
      "dataset": "ny_elevator_contractor_licenses",
      "domain": "data.ny.gov",
      "fxf": "jrac-r9vc",
      "source_code": "socrata_jrac-r9vc",
      "status": "caught_up",
      "inserted": 0,
      "fetched": 297,
      "mapped_cols": [
        "name",
        "phone",
        "addr_line1",
        "city",
        "region",
        "postal",
        "category"
      ]
    },
    {
      "dataset": "oregon_active_businesses_all",
      "domain": "data.oregon.gov",
      "fxf": "tckn-sxa6",
      "source_code": "socrata_tckn-sxa6",
      "status": "caught_up",
      "inserted": 0,
      "fetched": 2000,
      "mapped_cols": [
        "name",
        "addr_line1",
        "city",
        "region",
        "postal"
      ]
    },
    {
      "dataset": "oregon_active_contractor_licenses",
      "domain": "data.oregon.gov",
      "fxf": "vhbr-cuaq",
      "status": "no_name_col",
      "cols": [
        ":id",
        ":created_at",
        ":updated_at",
        ":version",
        "licnbr",
        "profession",
        "lictype",
        "full_name"
      ]
    },
    {
      "dataset": "pa_registered_businesses_by_county",
      "domain": "data.pa.gov",
      "fxf": "xvd7-5r2c",
      "source_code": "socrata_xvd7-5r2c",
      "status": "live",
      "inserted": 2000,
      "fetched": 2000,
      "mapped_cols": [
        "name",
        "city",
        "region",
        "postal"
      ]
    },
    {
      "dataset": "pa_sales_use_hotel_tax_licenses",
      "domain": "data.pa.gov",
      "fxf": "ugeq-ckxd",
      "source_code": "socrata_ugeq-ckxd",
      "status": "live",
      "inserted": 1255,
      "fetched": 1265,
      "mapped_cols": [
        "name",
        "addr_line1",
        "city",
        "region",
        "postal",
        "category"
      ]
    },
    {
      "dataset": "richmond_va_business_licenses",
      "domain": "data.richmondgov.com",
      "fxf": "hy5d-7dcv",
      "status": "no_name_col",
      "cols": [
        ":id",
        ":created_at",
        ":updated_at",
        ":version",
        "customer_s_name",
        "customer_s_address"
      ]
    },
    {
      "dataset": "cincinnati_business_licenses",
      "domain": "data.cincinnati-oh.gov",
      "fxf": "7dk3-gngs",
      "status": "no_name_col",
      "cols": [
        ":id",
        ":created_at",
        ":updated_at",
        ":version",
        "recnum",
        "license",
        "quantity",
        "business_number"
      ]
    },
    {
      "dataset": "berkeley_business_licenses",
      "domain": "data.cityofberkeley.info",
      "fxf": "rwnf-bu3w",
      "source_code": "socrata_rwnf-bu3w",
      "status": "caught_up",
      "inserted": 0,
      "fetched": 2000,
      "mapped_cols": [
        "name"
      ]
    },
    {
      "dataset": "henderson_nv_active_business_licenses",
      "domain": "performance.cityofhenderson.com",
      "fxf": "n8gp-u2pj",
      "source_code": "socrata_n8gp-u2pj",
      "status": "caught_up",
      "inserted": 0,
      "fetched": 2000,
      "mapped_cols": [
        "name",
        "category"
      ]
    },
    {
      "dataset": "texas_active_cigarette_tobacco_nonretailers",
      "domain": "data.texas.gov",
      "fxf": "mhvi-79zr",
      "source_code": "socrata_mhvi-79zr",
      "status": "live",
      "inserted": 695,
      "fetched": 695,
      "mapped_cols": [
        "name",
        "addr_line1",
        "city",
        "region",
        "postal"
      ]
    },
    {
      "dataset": "texas_approved_insurance_agencies",
      "domain": "data.texas.gov",
      "fxf": "3yqc-fcdt",
      "status": "no_name_col",
      "cols": [
        ":id",
        ":created_at",
        ":updated_at",
        ":version",
        "npn",
        "agency_license_number",
        "org_name",
        "agency_type"
      ]
    },
    {
      "dataset": "wa_lni_contractor_license_general",
      "domain": "data.wa.gov",
      "fxf": "m8qx-ubtq",
      "source_code": "socrata_m8qx-ubtq",
      "status": "caught_up",
      "inserted": 0,
      "fetched": 2000,
      "mapped_cols": [
        "name",
        "phone",
        "addr_line1",
        "city",
        "region",
        "postal"
      ]
    },
    {
      "dataset": "wa_lni_contractor_license_principal",
      "domain": "data.wa.gov",
      "fxf": "4xk5-x9j6",
      "source_code": "socrata_4xk5-x9j6",
      "status": "caught_up",
      "inserted": 0,
      "fetched": 2000,
      "mapped_cols": [
        "name"
      ]
    },
    {
      "dataset": "wa_dol_transportation_business_licenses",
      "domain": "data.wa.gov",
      "fxf": "ucdg-xgbj",
      "source_code": "socrata_ucdg-xgbj",
      "status": "empty_window",
      "inserted": 0,
      "fetched": 0,
      "mapped_cols": [
        "name",
        "phone",
        "city",
        "region",
        "category"
      ]
    },
    {
      "dataset": "wa_lcb_cannabis_renewal",
      "domain": "data.wa.gov",
      "fxf": "brpd-b6zd",
      "source_code": "socrata_brpd-b6zd",
      "status": "live",
      "inserted": 134,
      "fetched": 134,
      "mapped_cols": [
        "city",
        "region",
        "postal",
        "name"
      ]
    },
    {
      "dataset": "lacity_listing_all_businesses",
      "domain": "data.lacity.org",
      "fxf": "r4uk-afju",
      "source_code": "socrata_r4uk-afju",
      "status": "live",
      "inserted": 1,
      "fetched": 1,
      "mapped_cols": [
        "name",
        "addr_line1",
        "city",
        "postal"
      ]
    },
    {
      "dataset": "montgomery_md_door_to_door_vendor_license",
      "domain": "data.montgomerycountymd.gov",
      "fxf": "99mh-igdc",
      "source_code": "socrata_99mh-igdc",
      "status": "caught_up",
      "inserted": 0,
      "fetched": 1,
      "mapped_cols": [
        "name",
        "category"
      ]
    },
    {
      "dataset": "kcmo_food_permits",
      "domain": "data.kcmo.org",
      "fxf": "sz9c-c5ux",
      "source_code": "socrata_sz9c-c5ux",
      "status": "empty_window",
      "inserted": 0,
      "fetched": 0,
      "mapped_cols": [
        "name"
      ]
    },
    {
      "dataset": "utah_licensed_medical_cannabis_pharmacies",
      "domain": "opendata.utah.gov",
      "fxf": "9r9p-6sh4",
      "source_code": "socrata_9r9p-6sh4",
      "status": "empty_window",
      "inserted": 0,
      "fetched": 0,
      "mapped_cols": [
        "name",
        "addr_line1",
        "city",
        "region"
      ]
    }
  ],
  "honesty": "a source counts LIVE only if it wrote real rows this run. caught_up=mapped+fetched but 0 new (dedup). no_name_col=no business-name column. http_4xx/err=fetch failed."
}